celeste_image_generation/__init__.py
celeste_image_generation/client.py
celeste_image_generation/constraints.py
celeste_image_generation/io.py
celeste_image_generation/models.py
celeste_image_generation/parameters.py
celeste_image_generation/py.typed
celeste_image_generation/streaming.py
celeste_image_generation/providers/__init__.py
celeste_image_generation/providers/bfl/__init__.py
celeste_image_generation/providers/bfl/client.py
celeste_image_generation/providers/bfl/models.py
celeste_image_generation/providers/bfl/parameters.py
celeste_image_generation/providers/byteplus/README.md
celeste_image_generation/providers/byteplus/__init__.py
celeste_image_generation/providers/byteplus/client.py
celeste_image_generation/providers/byteplus/models.py
celeste_image_generation/providers/byteplus/parameters.py
celeste_image_generation/providers/byteplus/streaming.py
celeste_image_generation/providers/google/__init__.py
celeste_image_generation/providers/google/client.py
celeste_image_generation/providers/google/gemini.py
celeste_image_generation/providers/google/gemini_parameters.py
celeste_image_generation/providers/google/imagen.py
celeste_image_generation/providers/google/imagen_parameters.py
celeste_image_generation/providers/google/models.py
celeste_image_generation/providers/google/parameters.py
celeste_image_generation/providers/openai/__init__.py
celeste_image_generation/providers/openai/client.py
celeste_image_generation/providers/openai/models.py
celeste_image_generation/providers/openai/parameters.py
celeste_image_generation/providers/openai/streaming.py
celeste_image_generation-0.3.7.dist-info/METADATA
celeste_image_generation-0.3.7.dist-info/WHEEL
celeste_image_generation-0.3.7.dist-info/entry_points.txt
celeste_image_generation-0.3.7.dist-info/RECORD
